Metadata-Version: 2.1
Name: GoFUSE
Version: 0.0.5
Summary: GoFUSE is a pyfuse / xmlrpc based distributed filesystem.
Home-page: https://pypi.org/project/GoFUSE/0.0.1/
Author: Georg Gogo. BERNHARD
Author-email: gogo@bluedynamics.com
License: GPL
Platform: UNKNOWN
